backend/__init__.py
backend/environments.py
backend/http.py
backend/local_storage.py
backend/session_manager.py
backend/types.py
backend/websocket.py
backend/chat/__init__.py
backend/chat/chats_handler.py
backend/chat/dm/__init__.py
backend/chat/dm/dm_handler.py
backend/login/__init__.py
backend/login/login_model.py
chatenium_uniend-0.2.1.dist-info/licenses/LICENSE
chatenium_uniend-0.2.1.dist-info/METADATA
chatenium_uniend-0.2.1.dist-info/WHEEL
chatenium_uniend-0.2.1.dist-info/top_level.txt
chatenium_uniend-0.2.1.dist-info/RECORD
