Metadata-Version: 2.4
Name: chatenium-uniend
Version: 0.2.1
Summary: Linux-only GPL-3 backend package for Chatenium
License-Expression: GPL-3.0-or-later
Classifier: Programming Language :: Python :: 3
Classifier: Operating System :: POSIX :: Linux
Requires-Python: >=3.10
License-File: LICENSE
Requires-Dist: requests>=2.31
Requires-Dist: keyring>=24.0
Requires-Dist: aiohttp>=3.9
Requires-Dist: websocket-client>=1.9.0
Requires-Dist: rel>=0.4.9.23
Dynamic: license-file
